bdffont/__init__.py
bdffont/error.py
bdffont/font.py
bdffont/glyph.py
bdffont/properties.py
bdffont-0.0.35.dist-info/WHEEL
bdffont-0.0.35.dist-info/METADATA
bdffont-0.0.35.dist-info/RECORD
